mycorrhiza/__init__.py
mycorrhiza/exceptions.py
mycorrhiza/helper.py
mycorrhiza/scripts.py
mycorrhiza/settings.py
mycorrhiza/analysis/__init__.py
mycorrhiza/analysis/analysis.py
mycorrhiza/analysis/crossvalidate.py
mycorrhiza/analysis/supervised.py
mycorrhiza/dataset/__init__.py
mycorrhiza/dataset/dataset.py
mycorrhiza/dataset/myco.py
mycorrhiza/dataset/nexus.py
mycorrhiza/dataset/parse.py
mycorrhiza/dataset/structure.py
mycorrhiza/dataset/vcf.py
mycorrhiza/network/__init__.py
mycorrhiza/network/network.py
mycorrhiza/plotting/__init__.py
mycorrhiza/plotting/plotting.py
mycorrhiza-0.0.28.dist-info/DESCRIPTION.rst
mycorrhiza-0.0.28.dist-info/METADATA
mycorrhiza-0.0.28.dist-info/RECORD
mycorrhiza-0.0.28.dist-info/WHEEL
mycorrhiza-0.0.28.dist-info/entry_points.txt
mycorrhiza-0.0.28.dist-info/metadata.json
mycorrhiza-0.0.28.dist-info/top_level.txt
