Metadata-Version: 2.0
Name: mycorrhiza
Version: 0.0.28
Summary: Mycorrhiza population assignment tools.
Home-page: https://github.com/jgeofil/mycorrhiza
Author: Jeremy Georges-Filteau
Author-email: jeremy.georges-filteau@mail.mcgill.ca
License: UNKNOWN
Platform: UNKNOWN
Classifier: Programming Language :: Python :: 3
Classifier: License :: OSI Approved :: GNU Lesser General Public License v3 (LGPLv3)
Classifier: Operating System :: OS Independent
Requires-Python: >=3
Requires-Dist: matplotlib
Requires-Dist: numpy
Requires-Dist: pathos
Requires-Dist: scikit-learn
Requires-Dist: scipy
Requires-Dist: tqdm
